dot2mermaid/__init__.py
dot2mermaid/dot2mermaid.py
dot2mermaid-0.3.0.dist-info/LICENSE
dot2mermaid-0.3.0.dist-info/METADATA
dot2mermaid-0.3.0.dist-info/WHEEL
dot2mermaid-0.3.0.dist-info/RECORD
