Metadata-Version: 2.1
Name: dot2mermaid
Version: 0.3.0
Summary: A library for converting dot file to mermaid and markdown.
Home-page: https://github.com/HoseynAAmiri
License: MIT
Author: Hoseyn A. Amiri
Requires-Python: >=3.11,<4.0
Classifier: License :: OSI Approved :: MIT License
Classifier: Programming Language :: Python :: 3
Classifier: Programming Language :: Python :: 3.11
Classifier: Programming Language :: Python :: 3.12
Requires-Dist: code2flow (>=2.5.1,<3.0.0)
Requires-Dist: pygraphviz (>=1.13,<2.0)
Project-URL: Documentation, https://www.youtube.com/@hoseynamiri
Project-URL: Repository, https://github.com/HoseynAAmiri/dot2mermaid
